matrix_package/Structure_Factor.py
matrix_package/__init__.py
matrix_package/bin.py
matrix_package/com.py
matrix_package/control.py
matrix_package/coordinates_transform.py
matrix_package/density.py
matrix_package/density_test.py
matrix_package/gdr.py
matrix_package/get_file.py
matrix_package/molecule.py
matrix_package/params.py
matrix_package/pbc.py
matrix_package/periodic_bc.py
matrix_package/scale.py
matrix_package-23.4.29.dist-info/LICENCE
matrix_package-23.4.29.dist-info/METADATA
matrix_package-23.4.29.dist-info/WHEEL
matrix_package-23.4.29.dist-info/top_level.txt
matrix_package-23.4.29.dist-info/RECORD
