Metadata-Version: 2.1
Name: matrix-package
Version: 23.4.29
Summary: Molecular dynamics code for the analysis of structural, dynamic, thermodynamic and electronic properties of certain 2D materials.
Home-page: https://github.com/amieheessomba
Author: Iréné Amiehe-Essomba 
Author-email: ibamieheessomba@unistra.fr
License: IPCMS
Keywords: molecular dynamics matrix package
Platform: UNKNOWN
License-File: LICENCE
Requires-Dist: markdown
